{"manifest":{"serviceId":"es","accessType":"publish","hawkFilePublicationDate":"2024-08-24T11:11:59Z","ETLIngestionTriggerDate":"2024-08-24T13:26:26Z","currencyCode":"USD","source":"es-reservedinstance"},"regions":{"US West (Oregon)":{"m6g 2xlarge.search General purpose 1 year No Upfront":{"rateCode":"3UHPEXEPGG45RF3A.4NA7Y494T4.6YS6EN2CT7","price":"0.3530000000","vCPU":"8","Storage":"EBS Only","Memory (GiB)":"32","Instance Type":"m6g.2xlarge.search","Location":"US West (Oregon)","LeaseContractLength":"1yr","plc:LeaseContractLength":"1 year","PurchaseOption":"No Upfront","Instance Family":"General purpose","OnDemand:InstanceType":"m6g.2xlarge.search","OnDemand:Location":"US West (Oregon)","OnDemand:PricePerUnit":"0.5110000000","OnDemand:RateCode":"3UHPEXEPGG45RF3A.JRTCKXETXF.6YS6EN2CT7"},"m6g 4xlarge.search General purpose 1 year No Upfront":{"rateCode":"83YDSBBYKKSUGUWB.4NA7Y494T4.6YS6EN2CT7","price":"0.7060000000","vCPU":"16","Storage":"EBS Only","Memory (GiB)":"64","Instance Type":"m6g.4xlarge.search","Location":"US West (Oregon)","LeaseContractLength":"1yr","plc:LeaseContractLength":"1 year","PurchaseOption":"No Upfront","Instance Family":"General purpose","OnDemand:InstanceType":"m6g.4xlarge.search","OnDemand:Location":"US West (Oregon)","OnDemand:PricePerUnit":"1.0230000000","OnDemand:RateCode":"83YDSBBYKKSUGUWB.JRTCKXETXF.6YS6EN2CT7"},"m5 large.search General purpose 1 year No Upfront":{"rateCode":"8HU6FSKSJVRTBRED.4NA7Y494T4.6YS6EN2CT7","price":"0.0980000000","vCPU":"2","Storage":"EBS Only","Memory (GiB)":"8","Instance Type":"m5.large.search","Location":"US West (Oregon)","LeaseContractLength":"1yr","plc:LeaseContractLength":"1 year","PurchaseOption":"No Upfront","Instance Family":"General purpose","OnDemand:InstanceType":"m5.large.search","OnDemand:Location":"US West (Oregon)","OnDemand:PricePerUnit":"0.1420000000","OnDemand:RateCode":"8HU6FSKSJVRTBRED.JRTCKXETXF.6YS6EN2CT7"},"m6g xlarge.search General purpose 1 year No Upfront":{"rateCode":"EWEZT777H5TSZ58B.4NA7Y494T4.6YS6EN2CT7","price":"0.1770000000","vCPU":"4","Storage":"EBS Only","Memory (GiB)":"16","Instance Type":"m6g.xlarge.search","Location":"US West (Oregon)","LeaseContractLength":"1yr","plc:LeaseContractLength":"1 year","PurchaseOption":"No Upfront","Instance Family":"General purpose","OnDemand:InstanceType":"m6g.xlarge.search","OnDemand:Location":"US West (Oregon)","OnDemand:PricePerUnit":"0.2560000000","OnDemand:RateCode":"EWEZT777H5TSZ58B.JRTCKXETXF.6YS6EN2CT7"},"m4 10xlarge.search General purpose 1 year No Upfront":{"rateCode":"GVZNQHA2CN2GKZ8C.4NA7Y494T4.6YS6EN2CT7","price":"2.0820000000","vCPU":"40","Storage":"EBS Only","Memory (GiB)":"160","Instance Type":"m4.10xlarge.search","Location":"US West (Oregon)","LeaseContractLength":"1yr","plc:LeaseContractLength":"1 year","PurchaseOption":"No Upfront","Instance Family":"General purpose","OnDemand:InstanceType":"m4.10xlarge.search","OnDemand:Location":"US West (Oregon)","OnDemand:PricePerUnit":"3.0170000000","OnDemand:RateCode":"GVZNQHA2CN2GKZ8C.JRTCKXETXF.6YS6EN2CT7"},"m5 12xlarge.search General purpose 1 year No Upfront":{"rateCode":"MUAY5B2NKV294MCA.4NA7Y494T4.6YS6EN2CT7","price":"2.3450000000","vCPU":"48","Storage":"EBS Only","Memory (GiB)":"192","Instance Type":"m5.12xlarge.search","Location":"US West (Oregon)","LeaseContractLength":"1yr","plc:LeaseContractLength":"1 year","PurchaseOption":"No Upfront","Instance Family":"General purpose","OnDemand:InstanceType":"m5.12xlarge.search","OnDemand:Location":"US West (Oregon)","OnDemand:PricePerUnit":"3.3980000000","OnDemand:RateCode":"MUAY5B2NKV294MCA.JRTCKXETXF.6YS6EN2CT7"},"m6g 12xlarge.search General purpose 1 year No Upfront":{"rateCode":"S369GC96AJ3ERBUB.4NA7Y494T4.6YS6EN2CT7","price":"2.1170000000","vCPU":"48","Storage":"EBS Only","Memory (GiB)":"192","Instance Type":"m6g.12xlarge.search","Location":"US West (Oregon)","LeaseContractLength":"1yr","plc:LeaseContractLength":"1 year","PurchaseOption":"No Upfront","Instance Family":"General purpose","OnDemand:InstanceType":"m6g.12xlarge.search","OnDemand:Location":"US West (Oregon)","OnDemand:PricePerUnit":"3.0680000000","OnDemand:RateCode":"S369GC96AJ3ERBUB.JRTCKXETXF.6YS6EN2CT7"},"m4 large.search General purpose 1 year No Upfront":{"rateCode":"S52AA6MRRZFRJFHF.4NA7Y494T4.6YS6EN2CT7","price":"0.1040000000","vCPU":"2","Storage":"EBS Only","Memory (GiB)":"8","Instance Type":"m4.large.search","Location":"US West (Oregon)","LeaseContractLength":"1yr","plc:LeaseContractLength":"1 year","PurchaseOption":"No Upfront","Instance Family":"General purpose","OnDemand:InstanceType":"m4.large.search","OnDemand:Location":"US West (Oregon)","OnDemand:PricePerUnit":"0.1510000000","OnDemand:RateCode":"S52AA6MRRZFRJFHF.JRTCKXETXF.6YS6EN2CT7"},"m4 2xlarge.search General purpose 1 year No Upfront":{"rateCode":"SYBX7Y59PWV639B9.4NA7Y494T4.6YS6EN2CT7","price":"0.4160000000","vCPU":"8","Storage":"EBS Only","Memory (GiB)":"32","Instance Type":"m4.2xlarge.search","Location":"US West (Oregon)","LeaseContractLength":"1yr","plc:LeaseContractLength":"1 year","PurchaseOption":"No Upfront","Instance Family":"General purpose","OnDemand:InstanceType":"m4.2xlarge.search","OnDemand:Location":"US West (Oregon)","OnDemand:PricePerUnit":"0.6030000000","OnDemand:RateCode":"SYBX7Y59PWV639B9.JRTCKXETXF.6YS6EN2CT7"},"t3 medium.search General purpose 1 year No Upfront":{"rateCode":"XNEZUE2336WDGP38.4NA7Y494T4.6YS6EN2CT7","price":"0.0600000000","vCPU":"2","Storage":"EBS Only","Memory (GiB)":"4","Instance Type":"t3.medium.search","Location":"US West (Oregon)","LeaseContractLength":"1yr","plc:LeaseContractLength":"1 year","PurchaseOption":"No Upfront","Instance Family":"General purpose","OnDemand:InstanceType":"t3.medium.search","OnDemand:Location":"US West (Oregon)","OnDemand:PricePerUnit":"0.0730000000","OnDemand:RateCode":"XNEZUE2336WDGP38.JRTCKXETXF.6YS6EN2CT7"},"m5 4xlarge.search General purpose 1 year No Upfront":{"rateCode":"YHSYKA4V3VBESG3J.4NA7Y494T4.6YS6EN2CT7","price":"0.7820000000","vCPU":"16","Storage":"EBS Only","Memory (GiB)":"64","Instance Type":"m5.4xlarge.search","Location":"US West (Oregon)","LeaseContractLength":"1yr","plc:LeaseContractLength":"1 year","PurchaseOption":"No Upfront","Instance Family":"General purpose","OnDemand:InstanceType":"m5.4xlarge.search","OnDemand:Location":"US West (Oregon)","OnDemand:PricePerUnit":"1.1330000000","OnDemand:RateCode":"YHSYKA4V3VBESG3J.JRTCKXETXF.6YS6EN2CT7"},"m4 xlarge.search General purpose 1 year No Upfront":{"rateCode":"9HXENACB2GMZEX8B.4NA7Y494T4.6YS6EN2CT7","price":"0.2080000000","vCPU":"4","Storage":"EBS Only","Memory (GiB)":"16","Instance Type":"m4.xlarge.search","Location":"US West (Oregon)","LeaseContractLength":"1yr","plc:LeaseContractLength":"1 year","PurchaseOption":"No Upfront","Instance Family":"General purpose","OnDemand:InstanceType":"m4.xlarge.search","OnDemand:Location":"US West (Oregon)","OnDemand:PricePerUnit":"0.3010000000","OnDemand:RateCode":"9HXENACB2GMZEX8B.JRTCKXETXF.6YS6EN2CT7"},"m6g large.search General purpose 1 year No Upfront":{"rateCode":"AJGND2R8QKVCR6SC.4NA7Y494T4.6YS6EN2CT7","price":"0.0880000000","vCPU":"2","Storage":"EBS Only","Memory (GiB)":"8","Instance Type":"m6g.large.search","Location":"US West (Oregon)","LeaseContractLength":"1yr","plc:LeaseContractLength":"1 year","PurchaseOption":"No Upfront","Instance Family":"General purpose","OnDemand:InstanceType":"m6g.large.search","OnDemand:Location":"US West (Oregon)","OnDemand:PricePerUnit":"0.1280000000","OnDemand:RateCode":"AJGND2R8QKVCR6SC.JRTCKXETXF.6YS6EN2CT7"},"m6g 8xlarge.search General purpose 1 year No Upfront":{"rateCode":"RPBJG6Q3HK7QEHGP.4NA7Y494T4.6YS6EN2CT7","price":"1.4110000000","vCPU":"32","Storage":"EBS Only","Memory (GiB)":"128","Instance Type":"m6g.8xlarge.search","Location":"US West (Oregon)","LeaseContractLength":"1yr","plc:LeaseContractLength":"1 year","PurchaseOption":"No Upfront","Instance Family":"General purpose","OnDemand:InstanceType":"m6g.8xlarge.search","OnDemand:Location":"US West (Oregon)","OnDemand:PricePerUnit":"2.0450000000","OnDemand:RateCode":"RPBJG6Q3HK7QEHGP.JRTCKXETXF.6YS6EN2CT7"},"m5 xlarge.search General purpose 1 year No Upfront":{"rateCode":"UVRKB3DMW8TNCASD.4NA7Y494T4.6YS6EN2CT7","price":"0.1950000000","vCPU":"4","Storage":"EBS Only","Memory (GiB)":"16","Instance Type":"m5.xlarge.search","Location":"US West (Oregon)","LeaseContractLength":"1yr","plc:LeaseContractLength":"1 year","PurchaseOption":"No Upfront","Instance Family":"General purpose","OnDemand:InstanceType":"m5.xlarge.search","OnDemand:Location":"US West (Oregon)","OnDemand:PricePerUnit":"0.2830000000","OnDemand:RateCode":"UVRKB3DMW8TNCASD.JRTCKXETXF.6YS6EN2CT7"},"m5 2xlarge.search General purpose 1 year No Upfront":{"rateCode":"X695AYT7FE2YU7Q4.4NA7Y494T4.6YS6EN2CT7","price":"0.3910000000","vCPU":"8","Storage":"EBS Only","Memory (GiB)":"32","Instance Type":"m5.2xlarge.search","Location":"US West (Oregon)","LeaseContractLength":"1yr","plc:LeaseContractLength":"1 year","PurchaseOption":"No Upfront","Instance Family":"General purpose","OnDemand:InstanceType":"m5.2xlarge.search","OnDemand:Location":"US West (Oregon)","OnDemand:PricePerUnit":"0.5660000000","OnDemand:RateCode":"X695AYT7FE2YU7Q4.JRTCKXETXF.6YS6EN2CT7"},"m4 4xlarge.search General purpose 1 year No Upfront":{"rateCode":"YDREAD6UGBWUPK4N.4NA7Y494T4.6YS6EN2CT7","price":"0.8330000000","vCPU":"16","Storage":"EBS Only","Memory (GiB)":"64","Instance Type":"m4.4xlarge.search","Location":"US West (Oregon)","LeaseContractLength":"1yr","plc:LeaseContractLength":"1 year","PurchaseOption":"No Upfront","Instance Family":"General purpose","OnDemand:InstanceType":"m4.4xlarge.search","OnDemand:Location":"US West (Oregon)","OnDemand:PricePerUnit":"1.2070000000","OnDemand:RateCode":"YDREAD6UGBWUPK4N.JRTCKXETXF.6YS6EN2CT7"}}},"sets":{"1 year No Upfront US West Oregon General purpose":["m6g 2xlarge.search General purpose 1 year No Upfront","m6g 4xlarge.search General purpose 1 year No Upfront","m5 large.search General purpose 1 year No Upfront","m6g xlarge.search General purpose 1 year No Upfront","m4 10xlarge.search General purpose 1 year No Upfront","m5 12xlarge.search General purpose 1 year No Upfront","m6g 12xlarge.search General purpose 1 year No Upfront","m4 large.search General purpose 1 year No Upfront","m4 2xlarge.search General purpose 1 year No Upfront","t3 medium.search General purpose 1 year No Upfront","m5 4xlarge.search General purpose 1 year No Upfront","m4 xlarge.search General purpose 1 year No Upfront","m6g large.search General purpose 1 year No Upfront","m6g 8xlarge.search General purpose 1 year No Upfront","m5 xlarge.search General purpose 1 year No Upfront","m5 2xlarge.search General purpose 1 year No Upfront","m4 4xlarge.search General purpose 1 year No Upfront"]}}