{"manifest":{"serviceId":"es","accessType":"publish","hawkFilePublicationDate":"2024-11-15T00:30:33Z","ETLIngestionTriggerDate":"2024-11-15T00:30:33Z","currencyCode":"USD","source":"es-reservedinstance"},"regions":{"AWS GovCloud (US)":{"i3 4xlarge.search Storage optimized 3 year No Upfront":{"rateCode":"C6HXAFQ794EBZCHD.BPH4J8HBKS.6YS6EN2CT7","price":"1.2460000000","vCPU":"16","Storage":"2 x 1900 NVMe SSD","Memory (GiB)":"122","Instance Type":"i3.4xlarge.search","Location":"AWS GovCloud (US)","LeaseContractLength":"3yr","plc:LeaseContractLength":"3 year","PurchaseOption":"No Upfront","Instance Family":"Storage optimized","OnDemand:InstanceType":"i3.4xlarge.search","OnDemand:Location":"AWS GovCloud (US)","OnDemand:PricePerUnit":"2.3960000000","OnDemand:RateCode":"C6HXAFQ794EBZCHD.JRTCKXETXF.6YS6EN2CT7"},"i4i large.search Storage optimized 3 year No Upfront":{"rateCode":"D8CHM5TD832BG5GQ.BPH4J8HBKS.6YS6EN2CT7","price":"0.1720000000","vCPU":"2","Storage":"1 x 468 Nitro SSD","Memory (GiB)":"16","Instance Type":"i4i.large.search","Location":"AWS GovCloud (US)","LeaseContractLength":"3yr","plc:LeaseContractLength":"3 year","PurchaseOption":"No Upfront","Instance Family":"Storage optimized","OnDemand:InstanceType":"i4i.large.search","OnDemand:Location":"AWS GovCloud (US)","OnDemand:PricePerUnit":"0.3310000000","OnDemand:RateCode":"D8CHM5TD832BG5GQ.JRTCKXETXF.6YS6EN2CT7"},"i3 8xlarge.search Storage optimized 3 year No Upfront":{"rateCode":"FRGYEV3M52MQ6N9C.BPH4J8HBKS.6YS6EN2CT7","price":"2.4920000000","vCPU":"32","Storage":"4 x 1900 NVMe SSD","Memory (GiB)":"244","Instance Type":"i3.8xlarge.search","Location":"AWS GovCloud (US)","LeaseContractLength":"3yr","plc:LeaseContractLength":"3 year","PurchaseOption":"No Upfront","Instance Family":"Storage optimized","OnDemand:InstanceType":"i3.8xlarge.search","OnDemand:Location":"AWS GovCloud (US)","OnDemand:PricePerUnit":"4.7930000000","OnDemand:RateCode":"FRGYEV3M52MQ6N9C.JRTCKXETXF.6YS6EN2CT7"},"i3 16xlarge.search Storage optimized 3 year No Upfront":{"rateCode":"M9VHE8MMK9TNKZ2R.BPH4J8HBKS.6YS6EN2CT7","price":"4.9840000000","vCPU":"64","Storage":"8 x 1900 NVMe SSD","Memory (GiB)":"488","Instance Type":"i3.16xlarge.search","Location":"AWS GovCloud (US)","LeaseContractLength":"3yr","plc:LeaseContractLength":"3 year","PurchaseOption":"No Upfront","Instance Family":"Storage optimized","OnDemand:InstanceType":"i3.16xlarge.search","OnDemand:Location":"AWS GovCloud (US)","OnDemand:PricePerUnit":"9.5840000000","OnDemand:RateCode":"M9VHE8MMK9TNKZ2R.JRTCKXETXF.6YS6EN2CT7"},"i4i 2xlarge.search Storage optimized 3 year No Upfront":{"rateCode":"QHQSAZCVK93BWS6S.BPH4J8HBKS.6YS6EN2CT7","price":"0.6880000000","vCPU":"8","Storage":"1 x 1,875 Nitro SSD","Memory (GiB)":"64","Instance Type":"i4i.2xlarge.search","Location":"AWS GovCloud (US)","LeaseContractLength":"3yr","plc:LeaseContractLength":"3 year","PurchaseOption":"No Upfront","Instance Family":"Storage optimized","OnDemand:InstanceType":"i4i.2xlarge.search","OnDemand:Location":"AWS GovCloud (US)","OnDemand:PricePerUnit":"1.3230000000","OnDemand:RateCode":"QHQSAZCVK93BWS6S.JRTCKXETXF.6YS6EN2CT7"},"i4i 8xlarge.search Storage optimized 3 year No Upfront":{"rateCode":"RGR6H9TGPSRU7S99.BPH4J8HBKS.6YS6EN2CT7","price":"2.7530000000","vCPU":"32","Storage":"2 x 3,750 Nitro SSD","Memory (GiB)":"256","Instance Type":"i4i.8xlarge.search","Location":"AWS GovCloud (US)","LeaseContractLength":"3yr","plc:LeaseContractLength":"3 year","PurchaseOption":"No Upfront","Instance Family":"Storage optimized","OnDemand:InstanceType":"i4i.8xlarge.search","OnDemand:Location":"AWS GovCloud (US)","OnDemand:PricePerUnit":"5.2940000000","OnDemand:RateCode":"RGR6H9TGPSRU7S99.JRTCKXETXF.6YS6EN2CT7"},"i4i 12xlarge.search Storage optimized 3 year No Upfront":{"rateCode":"SBQ2GAPZJNAWDKN3.BPH4J8HBKS.6YS6EN2CT7","price":"4.1290000000","vCPU":"48","Storage":"3 x 3,750 Nitro SSD","Memory (GiB)":"384","Instance Type":"i4i.12xlarge.search","Location":"AWS GovCloud (US)","LeaseContractLength":"3yr","plc:LeaseContractLength":"3 year","PurchaseOption":"No Upfront","Instance Family":"Storage optimized","OnDemand:InstanceType":"i4i.12xlarge.search","OnDemand:Location":"AWS GovCloud (US)","OnDemand:PricePerUnit":"7.9410000000","OnDemand:RateCode":"SBQ2GAPZJNAWDKN3.JRTCKXETXF.6YS6EN2CT7"},"i4i 16xlarge.search Storage optimized 3 year No Upfront":{"rateCode":"UVRZG3RVUGP67RU8.BPH4J8HBKS.6YS6EN2CT7","price":"5.5060000000","vCPU":"64","Storage":"4 x 3,750 Nitro SSD","Memory (GiB)":"512","Instance Type":"i4i.16xlarge.search","Location":"AWS GovCloud (US)","LeaseContractLength":"3yr","plc:LeaseContractLength":"3 year","PurchaseOption":"No Upfront","Instance Family":"Storage optimized","OnDemand:InstanceType":"i4i.16xlarge.search","OnDemand:Location":"AWS GovCloud (US)","OnDemand:PricePerUnit":"10.5890000000","OnDemand:RateCode":"UVRZG3RVUGP67RU8.JRTCKXETXF.6YS6EN2CT7"},"i3 xlarge.search Storage optimized 3 year No Upfront":{"rateCode":"XBXJEKKB45CFMCWB.BPH4J8HBKS.6YS6EN2CT7","price":"0.3110000000","vCPU":"4","Storage":"1 x 950 NVMe SSD","Memory (GiB)":"30.5","Instance Type":"i3.xlarge.search","Location":"AWS GovCloud (US)","LeaseContractLength":"3yr","plc:LeaseContractLength":"3 year","PurchaseOption":"No Upfront","Instance Family":"Storage optimized","OnDemand:InstanceType":"i3.xlarge.search","OnDemand:Location":"AWS GovCloud (US)","OnDemand:PricePerUnit":"0.5990000000","OnDemand:RateCode":"XBXJEKKB45CFMCWB.JRTCKXETXF.6YS6EN2CT7"},"i4i 24xlarge.search Storage optimized 3 year No Upfront":{"rateCode":"YWAGSAAGJZRYMK77.BPH4J8HBKS.6YS6EN2CT7","price":"8.2590000000","vCPU":"96","Storage":"6 x 3,750 Nitro SSD","Memory (GiB)":"768","Instance Type":"i4i.24xlarge.search","Location":"AWS GovCloud (US)","LeaseContractLength":"3yr","plc:LeaseContractLength":"3 year","PurchaseOption":"No Upfront","Instance Family":"Storage optimized","OnDemand:InstanceType":"i4i.24xlarge.search","OnDemand:Location":"AWS GovCloud (US)","OnDemand:PricePerUnit":"15.8820000000","OnDemand:RateCode":"YWAGSAAGJZRYMK77.JRTCKXETXF.6YS6EN2CT7"},"i4i 4xlarge.search Storage optimized 3 year No Upfront":{"rateCode":"BB2TXN6TSSJNS25G.BPH4J8HBKS.6YS6EN2CT7","price":"1.3760000000","vCPU":"16","Storage":"1 x 3,750 Nitro SSD","Memory (GiB)":"128","Instance Type":"i4i.4xlarge.search","Location":"AWS GovCloud (US)","LeaseContractLength":"3yr","plc:LeaseContractLength":"3 year","PurchaseOption":"No Upfront","Instance Family":"Storage optimized","OnDemand:InstanceType":"i4i.4xlarge.search","OnDemand:Location":"AWS GovCloud (US)","OnDemand:PricePerUnit":"2.6460000000","OnDemand:RateCode":"BB2TXN6TSSJNS25G.JRTCKXETXF.6YS6EN2CT7"},"i3 large.search Storage optimized 3 year No Upfront":{"rateCode":"EVMHJFD72JHDFZ4B.BPH4J8HBKS.6YS6EN2CT7","price":"0.1560000000","vCPU":"2","Storage":"1 x 475 NVMe SSD","Memory (GiB)":"15.25","Instance Type":"i3.large.search","Location":"AWS GovCloud (US)","LeaseContractLength":"3yr","plc:LeaseContractLength":"3 year","PurchaseOption":"No Upfront","Instance Family":"Storage optimized","OnDemand:InstanceType":"i3.large.search","OnDemand:Location":"AWS GovCloud (US)","OnDemand:PricePerUnit":"0.3000000000","OnDemand:RateCode":"EVMHJFD72JHDFZ4B.JRTCKXETXF.6YS6EN2CT7"},"i4i xlarge.search Storage optimized 3 year No Upfront":{"rateCode":"FT6A6UKUD2A4F2U4.BPH4J8HBKS.6YS6EN2CT7","price":"0.3440000000","vCPU":"4","Storage":"1 x 937 Nitro SSD","Memory (GiB)":"32","Instance Type":"i4i.xlarge.search","Location":"AWS GovCloud (US)","LeaseContractLength":"3yr","plc:LeaseContractLength":"3 year","PurchaseOption":"No Upfront","Instance Family":"Storage optimized","OnDemand:InstanceType":"i4i.xlarge.search","OnDemand:Location":"AWS GovCloud (US)","OnDemand:PricePerUnit":"0.6620000000","OnDemand:RateCode":"FT6A6UKUD2A4F2U4.JRTCKXETXF.6YS6EN2CT7"},"i3 2xlarge.search Storage optimized 3 year No Upfront":{"rateCode":"4A6FR83B9F64VVTE.BPH4J8HBKS.6YS6EN2CT7","price":"0.6230000000","vCPU":"8","Storage":"1 x 1900 NVMe SSD","Memory (GiB)":"61","Instance Type":"i3.2xlarge.search","Location":"AWS GovCloud (US)","LeaseContractLength":"3yr","plc:LeaseContractLength":"3 year","PurchaseOption":"No Upfront","Instance Family":"Storage optimized","OnDemand:InstanceType":"i3.2xlarge.search","OnDemand:Location":"AWS GovCloud (US)","OnDemand:PricePerUnit":"1.1980000000","OnDemand:RateCode":"4A6FR83B9F64VVTE.JRTCKXETXF.6YS6EN2CT7"},"i4i 32xlarge.search Storage optimized 3 year No Upfront":{"rateCode":"43TZ3V4M5AM889P9.BPH4J8HBKS.6YS6EN2CT7","price":"11.0120000000","vCPU":"128","Storage":"8 x 3,750 Nitro SSD","Memory (GiB)":"1024","Instance Type":"i4i.32xlarge.search","Location":"AWS GovCloud (US)","LeaseContractLength":"3yr","plc:LeaseContractLength":"3 year","PurchaseOption":"No Upfront","Instance Family":"Storage optimized","OnDemand:InstanceType":"i4i.32xlarge.search","OnDemand:Location":"AWS GovCloud (US)","OnDemand:PricePerUnit":"21.1760000000","OnDemand:RateCode":"43TZ3V4M5AM889P9.JRTCKXETXF.6YS6EN2CT7"}}},"sets":{"3 year No Upfront AWS GovCloud US Storage optimized":["i3 4xlarge.search Storage optimized 3 year No Upfront","i4i large.search Storage optimized 3 year No Upfront","i3 8xlarge.search Storage optimized 3 year No Upfront","i3 16xlarge.search Storage optimized 3 year No Upfront","i4i 2xlarge.search Storage optimized 3 year No Upfront","i4i 8xlarge.search Storage optimized 3 year No Upfront","i4i 12xlarge.search Storage optimized 3 year No Upfront","i4i 16xlarge.search Storage optimized 3 year No Upfront","i3 xlarge.search Storage optimized 3 year No Upfront","i4i 24xlarge.search Storage optimized 3 year No Upfront","i4i 4xlarge.search Storage optimized 3 year No Upfront","i3 large.search Storage optimized 3 year No Upfront","i4i xlarge.search Storage optimized 3 year No Upfront","i3 2xlarge.search Storage optimized 3 year No Upfront","i4i 32xlarge.search Storage optimized 3 year No Upfront"]}}