{"manifest":{"serviceId":"rds","accessType":"publish","hawkFilePublicationDate":"2024-12-07T01:05:33Z","ETLIngestionTriggerDate":"2024-12-09T21:46:16Z","currencyCode":"USD","source":"rds-postgresql-reservedinstance"},"regions":{"AWS GovCloud (US-East)":{"PostgreSQL No license required db t4g.medium General purpose Multi-AZ 3 year Partial Upfront":{"rateCode":"2AYUGXNNPUAJBP7U.38NPMPTW36.6YS6EN2CT7","price":"0.0310000000","Instance Type":"db.t4g.medium","LeaseContractLength":"3yr","plc:LeaseContractLength":"3 year","PurchaseOption":"Partial Upfront","Deployment Option":"Multi-AZ","Location":"AWS GovCloud (US-East)","Database Engine":"PostgreSQL","OnDemand:InstanceType":"db.t4g.medium","OnDemand:Location":"AWS GovCloud (US-East)","OnDemand:PricePerUnit":"0.1410000000","OnDemand:RateCode":"2AYUGXNNPUAJBP7U.JRTCKXETXF.6YS6EN2CT7","riupfront:InstanceType":"db.t4g.medium","riupfront:Location":"AWS GovCloud (US-East)","riupfront:PricePerUnit":"814","riupfront:RateCode":"2AYUGXNNPUAJBP7U.38NPMPTW36.2TG2D8R56U"},"PostgreSQL No license required db m5.2xlarge General purpose Multi-AZ 3 year Partial Upfront":{"rateCode":"4K5Q9BFVB58K6FBD.38NPMPTW36.6YS6EN2CT7","price":"0.3494000000","Instance Type":"db.m5.2xlarge","LeaseContractLength":"3yr","plc:LeaseContractLength":"3 year","PurchaseOption":"Partial Upfront","Deployment Option":"Multi-AZ","Location":"AWS GovCloud (US-East)","Database Engine":"PostgreSQL","OnDemand:InstanceType":"db.m5.2xlarge","OnDemand:Location":"AWS GovCloud (US-East)","OnDemand:PricePerUnit":"1.7000000000","OnDemand:RateCode":"4K5Q9BFVB58K6FBD.JRTCKXETXF.6YS6EN2CT7","riupfront:InstanceType":"db.m5.2xlarge","riupfront:Location":"AWS GovCloud (US-East)","riupfront:PricePerUnit":"9181.4053","riupfront:RateCode":"4K5Q9BFVB58K6FBD.38NPMPTW36.2TG2D8R56U"},"PostgreSQL No license required db m6g.16xlarge General purpose Multi-AZ 3 year Partial Upfront":{"rateCode":"4Q7RB9MP3STBZHBX.38NPMPTW36.6YS6EN2CT7","price":"2.4737000000","Instance Type":"db.m6g.16xlarge","LeaseContractLength":"3yr","plc:LeaseContractLength":"3 year","PurchaseOption":"Partial Upfront","Deployment Option":"Multi-AZ","Location":"AWS GovCloud (US-East)","Database Engine":"PostgreSQL","OnDemand:InstanceType":"db.m6g.16xlarge","OnDemand:Location":"AWS GovCloud (US-East)","OnDemand:PricePerUnit":"11.8910000000","OnDemand:RateCode":"4Q7RB9MP3STBZHBX.JRTCKXETXF.6YS6EN2CT7","riupfront:InstanceType":"db.m6g.16xlarge","riupfront:Location":"AWS GovCloud (US-East)","riupfront:PricePerUnit":"65008","riupfront:RateCode":"4Q7RB9MP3STBZHBX.38NPMPTW36.2TG2D8R56U"},"PostgreSQL No license required db t3.xlarge General purpose Multi-AZ 3 year Partial Upfront":{"rateCode":"5JFFMFGZF8VQWCTU.38NPMPTW36.6YS6EN2CT7","price":"0.1601000000","Instance Type":"db.t3.xlarge","LeaseContractLength":"3yr","plc:LeaseContractLength":"3 year","PurchaseOption":"Partial Upfront","Deployment Option":"Multi-AZ","Location":"AWS GovCloud (US-East)","Database Engine":"PostgreSQL","OnDemand:InstanceType":"db.t3.xlarge","OnDemand:Location":"AWS GovCloud (US-East)","OnDemand:PricePerUnit":"0.7000000000","OnDemand:RateCode":"5JFFMFGZF8VQWCTU.JRTCKXETXF.6YS6EN2CT7","riupfront:InstanceType":"db.t3.xlarge","riupfront:Location":"AWS GovCloud (US-East)","riupfront:PricePerUnit":"4206.9024","riupfront:RateCode":"5JFFMFGZF8VQWCTU.38NPMPTW36.2TG2D8R56U"},"PostgreSQL No license required db m5.24xlarge General purpose Multi-AZ 3 year Partial Upfront":{"rateCode":"6DYA27VRWQXNXP4Y.38NPMPTW36.6YS6EN2CT7","price":"4.1924000000","Instance Type":"db.m5.24xlarge","LeaseContractLength":"3yr","plc:LeaseContractLength":"3 year","PurchaseOption":"Partial Upfront","Deployment Option":"Multi-AZ","Location":"AWS GovCloud (US-East)","Database Engine":"PostgreSQL","OnDemand:InstanceType":"db.m5.24xlarge","OnDemand:Location":"AWS GovCloud (US-East)","OnDemand:PricePerUnit":"20.4500000000","OnDemand:RateCode":"6DYA27VRWQXNXP4Y.JRTCKXETXF.6YS6EN2CT7","riupfront:InstanceType":"db.m5.24xlarge","riupfront:Location":"AWS GovCloud (US-East)","riupfront:PricePerUnit":"110176.864","riupfront:RateCode":"6DYA27VRWQXNXP4Y.38NPMPTW36.2TG2D8R56U"},"PostgreSQL No license required db r6g.8xlarge Memory optimized Multi-AZ 3 year Partial Upfront":{"rateCode":"7E6JU3PZUZNS2FW4.38NPMPTW36.6YS6EN2CT7","price":"1.6460000000","Instance Type":"db.r6g.8xlarge","LeaseContractLength":"3yr","plc:LeaseContractLength":"3 year","PurchaseOption":"Partial Upfront","Deployment Option":"Multi-AZ","Location":"AWS GovCloud (US-East)","Database Engine":"PostgreSQL","OnDemand:InstanceType":"db.r6g.8xlarge","OnDemand:Location":"AWS GovCloud (US-East)","OnDemand:PricePerUnit":"8.6340000000","OnDemand:RateCode":"7E6JU3PZUZNS2FW4.JRTCKXETXF.6YS6EN2CT7","riupfront:InstanceType":"db.r6g.8xlarge","riupfront:Location":"AWS GovCloud (US-East)","riupfront:PricePerUnit":"43257","riupfront:RateCode":"7E6JU3PZUZNS2FW4.38NPMPTW36.2TG2D8R56U"},"PostgreSQL No license required db t4g.large General purpose Multi-AZ 3 year Partial Upfront":{"rateCode":"7NMVYJRHE4UJRS86.38NPMPTW36.6YS6EN2CT7","price":"0.0620000000","Instance Type":"db.t4g.large","LeaseContractLength":"3yr","plc:LeaseContractLength":"3 year","PurchaseOption":"Partial Upfront","Deployment Option":"Multi-AZ","Location":"AWS GovCloud (US-East)","Database Engine":"PostgreSQL","OnDemand:InstanceType":"db.t4g.large","OnDemand:Location":"AWS GovCloud (US-East)","OnDemand:PricePerUnit":"0.2820000000","OnDemand:RateCode":"7NMVYJRHE4UJRS86.JRTCKXETXF.6YS6EN2CT7","riupfront:InstanceType":"db.t4g.large","riupfront:Location":"AWS GovCloud (US-East)","riupfront:PricePerUnit":"1628","riupfront:RateCode":"7NMVYJRHE4UJRS86.38NPMPTW36.2TG2D8R56U"},"PostgreSQL No license required db r6g.large Memory optimized Multi-AZ 3 year Partial Upfront":{"rateCode":"8KTX3BC7YEXNSKN7.38NPMPTW36.6YS6EN2CT7","price":"0.1029000000","Instance Type":"db.r6g.large","LeaseContractLength":"3yr","plc:LeaseContractLength":"3 year","PurchaseOption":"Partial Upfront","Deployment Option":"Multi-AZ","Location":"AWS GovCloud (US-East)","Database Engine":"PostgreSQL","OnDemand:InstanceType":"db.r6g.large","OnDemand:Location":"AWS GovCloud (US-East)","OnDemand:PricePerUnit":"0.5400000000","OnDemand:RateCode":"8KTX3BC7YEXNSKN7.JRTCKXETXF.6YS6EN2CT7","riupfront:InstanceType":"db.r6g.large","riupfront:Location":"AWS GovCloud (US-East)","riupfront:PricePerUnit":"2704","riupfront:RateCode":"8KTX3BC7YEXNSKN7.38NPMPTW36.2TG2D8R56U"},"PostgreSQL No license required db r5.12xlarge Memory optimized Multi-AZ 3 year Partial Upfront":{"rateCode":"8M3KRE94FWYGBKFP.38NPMPTW36.6YS6EN2CT7","price":"2.7451000000","Instance Type":"db.r5.12xlarge","LeaseContractLength":"3yr","plc:LeaseContractLength":"3 year","PurchaseOption":"Partial Upfront","Deployment Option":"Multi-AZ","Location":"AWS GovCloud (US-East)","Database Engine":"PostgreSQL","OnDemand:InstanceType":"db.r5.12xlarge","OnDemand:Location":"AWS GovCloud (US-East)","OnDemand:PricePerUnit":"14.4500000000","OnDemand:RateCode":"8M3KRE94FWYGBKFP.JRTCKXETXF.6YS6EN2CT7","riupfront:InstanceType":"db.r5.12xlarge","riupfront:Location":"AWS GovCloud (US-East)","riupfront:PricePerUnit":"72141.7536","riupfront:RateCode":"8M3KRE94FWYGBKFP.38NPMPTW36.2TG2D8R56U"},"PostgreSQL No license required db t4g.xlarge General purpose Multi-AZ 3 year Partial Upfront":{"rateCode":"8YXRV2DX7FXPKTAN.38NPMPTW36.6YS6EN2CT7","price":"0.1239000000","Instance Type":"db.t4g.xlarge","LeaseContractLength":"3yr","plc:LeaseContractLength":"3 year","PurchaseOption":"Partial Upfront","Deployment Option":"Multi-AZ","Location":"AWS GovCloud (US-East)","Database Engine":"PostgreSQL","OnDemand:InstanceType":"db.t4g.xlarge","OnDemand:Location":"AWS GovCloud (US-East)","OnDemand:PricePerUnit":"0.5630000000","OnDemand:RateCode":"8YXRV2DX7FXPKTAN.JRTCKXETXF.6YS6EN2CT7","riupfront:InstanceType":"db.t4g.xlarge","riupfront:Location":"AWS GovCloud (US-East)","riupfront:PricePerUnit":"3256","riupfront:RateCode":"8YXRV2DX7FXPKTAN.38NPMPTW36.2TG2D8R56U"},"PostgreSQL No license required db r6g.xlarge Memory optimized Multi-AZ 3 year Partial Upfront":{"rateCode":"93A8UFVBXY4XU2QF.38NPMPTW36.6YS6EN2CT7","price":"0.2057000000","Instance Type":"db.r6g.xlarge","LeaseContractLength":"3yr","plc:LeaseContractLength":"3 year","PurchaseOption":"Partial Upfront","Deployment Option":"Multi-AZ","Location":"AWS GovCloud (US-East)","Database Engine":"PostgreSQL","OnDemand:InstanceType":"db.r6g.xlarge","OnDemand:Location":"AWS GovCloud (US-East)","OnDemand:PricePerUnit":"1.0790000000","OnDemand:RateCode":"93A8UFVBXY4XU2QF.JRTCKXETXF.6YS6EN2CT7","riupfront:InstanceType":"db.r6g.xlarge","riupfront:Location":"AWS GovCloud (US-East)","riupfront:PricePerUnit":"5407","riupfront:RateCode":"93A8UFVBXY4XU2QF.38NPMPTW36.2TG2D8R56U"},"PostgreSQL No license required db r5.8xlarge Memory optimized Multi-AZ 3 year Partial Upfront":{"rateCode":"95USV3V5UTZ6PVDG.38NPMPTW36.6YS6EN2CT7","price":"1.8301000000","Instance Type":"db.r5.8xlarge","LeaseContractLength":"3yr","plc:LeaseContractLength":"3 year","PurchaseOption":"Partial Upfront","Deployment Option":"Multi-AZ","Location":"AWS GovCloud (US-East)","Database Engine":"PostgreSQL","OnDemand:InstanceType":"db.r5.8xlarge","OnDemand:Location":"AWS GovCloud (US-East)","OnDemand:PricePerUnit":"9.6300000000","OnDemand:RateCode":"95USV3V5UTZ6PVDG.JRTCKXETXF.6YS6EN2CT7","riupfront:InstanceType":"db.r5.8xlarge","riupfront:Location":"AWS GovCloud (US-East)","riupfront:PricePerUnit":"48094.5024","riupfront:RateCode":"95USV3V5UTZ6PVDG.38NPMPTW36.2TG2D8R56U"},"PostgreSQL No license required db m5.16xlarge General purpose Multi-AZ 3 year Partial Upfront":{"rateCode":"BKQB4RYXPT4B4EPV.38NPMPTW36.6YS6EN2CT7","price":"2.7949000000","Instance Type":"db.m5.16xlarge","LeaseContractLength":"3yr","plc:LeaseContractLength":"3 year","PurchaseOption":"Partial Upfront","Deployment Option":"Multi-AZ","Location":"AWS GovCloud (US-East)","Database Engine":"PostgreSQL","OnDemand:InstanceType":"db.m5.16xlarge","OnDemand:Location":"AWS GovCloud (US-East)","OnDemand:PricePerUnit":"13.6300000000","OnDemand:RateCode":"BKQB4RYXPT4B4EPV.JRTCKXETXF.6YS6EN2CT7","riupfront:InstanceType":"db.m5.16xlarge","riupfront:Location":"AWS GovCloud (US-East)","riupfront:PricePerUnit":"73451.2427","riupfront:RateCode":"BKQB4RYXPT4B4EPV.38NPMPTW36.2TG2D8R56U"},"PostgreSQL No license required db t3.large General purpose Multi-AZ 3 year Partial Upfront":{"rateCode":"BUEN4CRAUQZYWYDS.38NPMPTW36.6YS6EN2CT7","price":"0.0800000000","Instance Type":"db.t3.large","LeaseContractLength":"3yr","plc:LeaseContractLength":"3 year","PurchaseOption":"Partial Upfront","Deployment Option":"Multi-AZ","Location":"AWS GovCloud (US-East)","Database Engine":"PostgreSQL","OnDemand:InstanceType":"db.t3.large","OnDemand:Location":"AWS GovCloud (US-East)","OnDemand:PricePerUnit":"0.3500000000","OnDemand:RateCode":"BUEN4CRAUQZYWYDS.JRTCKXETXF.6YS6EN2CT7","riupfront:InstanceType":"db.t3.large","riupfront:Location":"AWS GovCloud (US-East)","riupfront:PricePerUnit":"2103.4512","riupfront:RateCode":"BUEN4CRAUQZYWYDS.38NPMPTW36.2TG2D8R56U"},"PostgreSQL No license required db m6g.large General purpose Multi-AZ 3 year Partial Upfront":{"rateCode":"CGBJRVXR25GK75W4.38NPMPTW36.6YS6EN2CT7","price":"0.0773000000","Instance Type":"db.m6g.large","LeaseContractLength":"3yr","plc:LeaseContractLength":"3 year","PurchaseOption":"Partial Upfront","Deployment Option":"Multi-AZ","Location":"AWS GovCloud (US-East)","Database Engine":"PostgreSQL","OnDemand:InstanceType":"db.m6g.large","OnDemand:Location":"AWS GovCloud (US-East)","OnDemand:PricePerUnit":"0.3720000000","OnDemand:RateCode":"CGBJRVXR25GK75W4.JRTCKXETXF.6YS6EN2CT7","riupfront:InstanceType":"db.m6g.large","riupfront:Location":"AWS GovCloud (US-East)","riupfront:PricePerUnit":"2032","riupfront:RateCode":"CGBJRVXR25GK75W4.38NPMPTW36.2TG2D8R56U"},"PostgreSQL No license required db r5.16xlarge Memory optimized Multi-AZ 3 year Partial Upfront":{"rateCode":"DF8TQYUQNXMW2VYY.38NPMPTW36.6YS6EN2CT7","price":"3.6602000000","Instance Type":"db.r5.16xlarge","LeaseContractLength":"3yr","plc:LeaseContractLength":"3 year","PurchaseOption":"Partial Upfront","Deployment Option":"Multi-AZ","Location":"AWS GovCloud (US-East)","Database Engine":"PostgreSQL","OnDemand:InstanceType":"db.r5.16xlarge","OnDemand:Location":"AWS GovCloud (US-East)","OnDemand:PricePerUnit":"19.2600000000","OnDemand:RateCode":"DF8TQYUQNXMW2VYY.JRTCKXETXF.6YS6EN2CT7","riupfront:InstanceType":"db.r5.16xlarge","riupfront:Location":"AWS GovCloud (US-East)","riupfront:PricePerUnit":"96189.0048","riupfront:RateCode":"DF8TQYUQNXMW2VYY.38NPMPTW36.2TG2D8R56U"},"PostgreSQL No license required db r5.4xlarge Memory optimized Multi-AZ 3 year Partial Upfront":{"rateCode":"E5BGDUEDHVNUA8PD.38NPMPTW36.6YS6EN2CT7","price":"0.9150000000","Instance Type":"db.r5.4xlarge","LeaseContractLength":"3yr","plc:LeaseContractLength":"3 year","PurchaseOption":"Partial Upfront","Deployment Option":"Multi-AZ","Location":"AWS GovCloud (US-East)","Database Engine":"PostgreSQL","OnDemand:InstanceType":"db.r5.4xlarge","OnDemand:Location":"AWS GovCloud (US-East)","OnDemand:PricePerUnit":"4.8200000000","OnDemand:RateCode":"E5BGDUEDHVNUA8PD.JRTCKXETXF.6YS6EN2CT7","riupfront:InstanceType":"db.r5.4xlarge","riupfront:Location":"AWS GovCloud (US-East)","riupfront:PricePerUnit":"24047.2512","riupfront:RateCode":"E5BGDUEDHVNUA8PD.38NPMPTW36.2TG2D8R56U"},"PostgreSQL No license required db r6g.12xlarge Memory optimized Multi-AZ 3 year Partial Upfront":{"rateCode":"GA39WSYY35RJABDA.38NPMPTW36.6YS6EN2CT7","price":"2.4690000000","Instance Type":"db.r6g.12xlarge","LeaseContractLength":"3yr","plc:LeaseContractLength":"3 year","PurchaseOption":"Partial Upfront","Deployment Option":"Multi-AZ","Location":"AWS GovCloud (US-East)","Database Engine":"PostgreSQL","OnDemand:InstanceType":"db.r6g.12xlarge","OnDemand:Location":"AWS GovCloud (US-East)","OnDemand:PricePerUnit":"12.9500000000","OnDemand:RateCode":"GA39WSYY35RJABDA.JRTCKXETXF.6YS6EN2CT7","riupfront:InstanceType":"db.r6g.12xlarge","riupfront:Location":"AWS GovCloud (US-East)","riupfront:PricePerUnit":"64885","riupfront:RateCode":"GA39WSYY35RJABDA.38NPMPTW36.2TG2D8R56U"},"PostgreSQL No license required db r5.large Memory optimized Multi-AZ 3 year Partial Upfront":{"rateCode":"H2ECXU2GZ7A4YS3S.38NPMPTW36.6YS6EN2CT7","price":"0.1144000000","Instance Type":"db.r5.large","LeaseContractLength":"3yr","plc:LeaseContractLength":"3 year","PurchaseOption":"Partial Upfront","Deployment Option":"Multi-AZ","Location":"AWS GovCloud (US-East)","Database Engine":"PostgreSQL","OnDemand:InstanceType":"db.r5.large","OnDemand:Location":"AWS GovCloud (US-East)","OnDemand:PricePerUnit":"0.6000000000","OnDemand:RateCode":"H2ECXU2GZ7A4YS3S.JRTCKXETXF.6YS6EN2CT7","riupfront:InstanceType":"db.r5.large","riupfront:Location":"AWS GovCloud (US-East)","riupfront:PricePerUnit":"3005.9064","riupfront:RateCode":"H2ECXU2GZ7A4YS3S.38NPMPTW36.2TG2D8R56U"},"PostgreSQL No license required db t3.medium General purpose Multi-AZ 3 year Partial Upfront":{"rateCode":"HA4XMCRSB3WNVES7.38NPMPTW36.6YS6EN2CT7","price":"0.0400000000","Instance Type":"db.t3.medium","LeaseContractLength":"3yr","plc:LeaseContractLength":"3 year","PurchaseOption":"Partial Upfront","Deployment Option":"Multi-AZ","Location":"AWS GovCloud (US-East)","Database Engine":"PostgreSQL","OnDemand:InstanceType":"db.t3.medium","OnDemand:Location":"AWS GovCloud (US-East)","OnDemand:PricePerUnit":"0.1700000000","OnDemand:RateCode":"HA4XMCRSB3WNVES7.JRTCKXETXF.6YS6EN2CT7","riupfront:InstanceType":"db.t3.medium","riupfront:Location":"AWS GovCloud (US-East)","riupfront:PricePerUnit":"1051.7256","riupfront:RateCode":"HA4XMCRSB3WNVES7.38NPMPTW36.2TG2D8R56U"},"PostgreSQL No license required db m6g.2xlarge General purpose Multi-AZ 3 year Partial Upfront":{"rateCode":"HJY6WJPRAEJ6YFW6.38NPMPTW36.6YS6EN2CT7","price":"0.3092000000","Instance Type":"db.m6g.2xlarge","LeaseContractLength":"3yr","plc:LeaseContractLength":"3 year","PurchaseOption":"Partial Upfront","Deployment Option":"Multi-AZ","Location":"AWS GovCloud (US-East)","Database Engine":"PostgreSQL","OnDemand:InstanceType":"db.m6g.2xlarge","OnDemand:Location":"AWS GovCloud (US-East)","OnDemand:PricePerUnit":"1.4860000000","OnDemand:RateCode":"HJY6WJPRAEJ6YFW6.JRTCKXETXF.6YS6EN2CT7","riupfront:InstanceType":"db.m6g.2xlarge","riupfront:Location":"AWS GovCloud (US-East)","riupfront:PricePerUnit":"8126","riupfront:RateCode":"HJY6WJPRAEJ6YFW6.38NPMPTW36.2TG2D8R56U"},"PostgreSQL No license required db m5.xlarge General purpose Multi-AZ 3 year Partial Upfront":{"rateCode":"HWU3NR6ECU945ZKX.38NPMPTW36.6YS6EN2CT7","price":"0.1747000000","Instance Type":"db.m5.xlarge","LeaseContractLength":"3yr","plc:LeaseContractLength":"3 year","PurchaseOption":"Partial Upfront","Deployment Option":"Multi-AZ","Location":"AWS GovCloud (US-East)","Database Engine":"PostgreSQL","OnDemand:InstanceType":"db.m5.xlarge","OnDemand:Location":"AWS GovCloud (US-East)","OnDemand:PricePerUnit":"0.8500000000","OnDemand:RateCode":"HWU3NR6ECU945ZKX.JRTCKXETXF.6YS6EN2CT7","riupfront:InstanceType":"db.m5.xlarge","riupfront:Location":"AWS GovCloud (US-East)","riupfront:PricePerUnit":"4590.7027","riupfront:RateCode":"HWU3NR6ECU945ZKX.38NPMPTW36.2TG2D8R56U"},"PostgreSQL No license required db m6g.8xlarge General purpose Multi-AZ 3 year Partial Upfront":{"rateCode":"KTP289BTDHH62ZPJ.38NPMPTW36.6YS6EN2CT7","price":"1.2368000000","Instance Type":"db.m6g.8xlarge","LeaseContractLength":"3yr","plc:LeaseContractLength":"3 year","PurchaseOption":"Partial Upfront","Deployment Option":"Multi-AZ","Location":"AWS GovCloud (US-East)","Database Engine":"PostgreSQL","OnDemand:InstanceType":"db.m6g.8xlarge","OnDemand:Location":"AWS GovCloud (US-East)","OnDemand:PricePerUnit":"5.9460000000","OnDemand:RateCode":"KTP289BTDHH62ZPJ.JRTCKXETXF.6YS6EN2CT7","riupfront:InstanceType":"db.m6g.8xlarge","riupfront:Location":"AWS GovCloud (US-East)","riupfront:PricePerUnit":"32504","riupfront:RateCode":"KTP289BTDHH62ZPJ.38NPMPTW36.2TG2D8R56U"},"PostgreSQL No license required db m6g.4xlarge General purpose Multi-AZ 3 year Partial Upfront":{"rateCode":"MHVQCM6EE6NY8AMX.38NPMPTW36.6YS6EN2CT7","price":"0.6184000000","Instance Type":"db.m6g.4xlarge","LeaseContractLength":"3yr","plc:LeaseContractLength":"3 year","PurchaseOption":"Partial Upfront","Deployment Option":"Multi-AZ","Location":"AWS GovCloud (US-East)","Database Engine":"PostgreSQL","OnDemand:InstanceType":"db.m6g.4xlarge","OnDemand:Location":"AWS GovCloud (US-East)","OnDemand:PricePerUnit":"2.9730000000","OnDemand:RateCode":"MHVQCM6EE6NY8AMX.JRTCKXETXF.6YS6EN2CT7","riupfront:InstanceType":"db.m6g.4xlarge","riupfront:Location":"AWS GovCloud (US-East)","riupfront:PricePerUnit":"16252","riupfront:RateCode":"MHVQCM6EE6NY8AMX.38NPMPTW36.2TG2D8R56U"},"PostgreSQL No license required db m5.large General purpose Multi-AZ 3 year Partial Upfront":{"rateCode":"NE9TWW7NBCMFWASA.38NPMPTW36.6YS6EN2CT7","price":"0.0873000000","Instance Type":"db.m5.large","LeaseContractLength":"3yr","plc:LeaseContractLength":"3 year","PurchaseOption":"Partial Upfront","Deployment Option":"Multi-AZ","Location":"AWS GovCloud (US-East)","Database Engine":"PostgreSQL","OnDemand:InstanceType":"db.m5.large","OnDemand:Location":"AWS GovCloud (US-East)","OnDemand:PricePerUnit":"0.4300000000","OnDemand:RateCode":"NE9TWW7NBCMFWASA.JRTCKXETXF.6YS6EN2CT7","riupfront:InstanceType":"db.m5.large","riupfront:Location":"AWS GovCloud (US-East)","riupfront:PricePerUnit":"2295.3513","riupfront:RateCode":"NE9TWW7NBCMFWASA.38NPMPTW36.2TG2D8R56U"},"PostgreSQL No license required db r5.xlarge Memory optimized Multi-AZ 3 year Partial Upfront":{"rateCode":"NTTEBNTR9ZB6QV77.38NPMPTW36.6YS6EN2CT7","price":"0.2288000000","Instance Type":"db.r5.xlarge","LeaseContractLength":"3yr","plc:LeaseContractLength":"3 year","PurchaseOption":"Partial Upfront","Deployment Option":"Multi-AZ","Location":"AWS GovCloud (US-East)","Database Engine":"PostgreSQL","OnDemand:InstanceType":"db.r5.xlarge","OnDemand:Location":"AWS GovCloud (US-East)","OnDemand:PricePerUnit":"1.2000000000","OnDemand:RateCode":"NTTEBNTR9ZB6QV77.JRTCKXETXF.6YS6EN2CT7","riupfront:InstanceType":"db.r5.xlarge","riupfront:Location":"AWS GovCloud (US-East)","riupfront:PricePerUnit":"6011.8128","riupfront:RateCode":"NTTEBNTR9ZB6QV77.38NPMPTW36.2TG2D8R56U"},"PostgreSQL No license required db m6g.12xlarge General purpose Multi-AZ 3 year Partial Upfront":{"rateCode":"PJ4YCCAK8RH4AJSY.38NPMPTW36.6YS6EN2CT7","price":"1.8553000000","Instance Type":"db.m6g.12xlarge","LeaseContractLength":"3yr","plc:LeaseContractLength":"3 year","PurchaseOption":"Partial Upfront","Deployment Option":"Multi-AZ","Location":"AWS GovCloud (US-East)","Database Engine":"PostgreSQL","OnDemand:InstanceType":"db.m6g.12xlarge","OnDemand:Location":"AWS GovCloud (US-East)","OnDemand:PricePerUnit":"8.9180000000","OnDemand:RateCode":"PJ4YCCAK8RH4AJSY.JRTCKXETXF.6YS6EN2CT7","riupfront:InstanceType":"db.m6g.12xlarge","riupfront:Location":"AWS GovCloud (US-East)","riupfront:PricePerUnit":"48756","riupfront:RateCode":"PJ4YCCAK8RH4AJSY.38NPMPTW36.2TG2D8R56U"},"PostgreSQL No license required db m6g.xlarge General purpose Multi-AZ 3 year Partial Upfront":{"rateCode":"QFBRZ6KHVW7KS4X6.38NPMPTW36.6YS6EN2CT7","price":"0.1546000000","Instance Type":"db.m6g.xlarge","LeaseContractLength":"3yr","plc:LeaseContractLength":"3 year","PurchaseOption":"Partial Upfront","Deployment Option":"Multi-AZ","Location":"AWS GovCloud (US-East)","Database Engine":"PostgreSQL","OnDemand:InstanceType":"db.m6g.xlarge","OnDemand:Location":"AWS GovCloud (US-East)","OnDemand:PricePerUnit":"0.7430000000","OnDemand:RateCode":"QFBRZ6KHVW7KS4X6.JRTCKXETXF.6YS6EN2CT7","riupfront:InstanceType":"db.m6g.xlarge","riupfront:Location":"AWS GovCloud (US-East)","riupfront:PricePerUnit":"4063","riupfront:RateCode":"QFBRZ6KHVW7KS4X6.38NPMPTW36.2TG2D8R56U"},"PostgreSQL No license required db t4g.small General purpose Multi-AZ 3 year Partial Upfront":{"rateCode":"QFDZPZUYEHWJSEJV.38NPMPTW36.6YS6EN2CT7","price":"0.0155000000","Instance Type":"db.t4g.small","LeaseContractLength":"3yr","plc:LeaseContractLength":"3 year","PurchaseOption":"Partial Upfront","Deployment Option":"Multi-AZ","Location":"AWS GovCloud (US-East)","Database Engine":"PostgreSQL","OnDemand:InstanceType":"db.t4g.small","OnDemand:Location":"AWS GovCloud (US-East)","OnDemand:PricePerUnit":"0.0700000000","OnDemand:RateCode":"QFDZPZUYEHWJSEJV.JRTCKXETXF.6YS6EN2CT7","riupfront:InstanceType":"db.t4g.small","riupfront:Location":"AWS GovCloud (US-East)","riupfront:PricePerUnit":"407","riupfront:RateCode":"QFDZPZUYEHWJSEJV.38NPMPTW36.2TG2D8R56U"},"PostgreSQL No license required db r6g.4xlarge Memory optimized Multi-AZ 3 year Partial Upfront":{"rateCode":"R9GYJQC2PBYU233J.38NPMPTW36.6YS6EN2CT7","price":"0.8230000000","Instance Type":"db.r6g.4xlarge","LeaseContractLength":"3yr","plc:LeaseContractLength":"3 year","PurchaseOption":"Partial Upfront","Deployment Option":"Multi-AZ","Location":"AWS GovCloud (US-East)","Database Engine":"PostgreSQL","OnDemand:InstanceType":"db.r6g.4xlarge","OnDemand:Location":"AWS GovCloud (US-East)","OnDemand:PricePerUnit":"4.3170000000","OnDemand:RateCode":"R9GYJQC2PBYU233J.JRTCKXETXF.6YS6EN2CT7","riupfront:InstanceType":"db.r6g.4xlarge","riupfront:Location":"AWS GovCloud (US-East)","riupfront:PricePerUnit":"21628","riupfront:RateCode":"R9GYJQC2PBYU233J.38NPMPTW36.2TG2D8R56U"},"PostgreSQL No license required db r5.24xlarge Memory optimized Multi-AZ 3 year Partial Upfront":{"rateCode":"RZHFZ83TE35UPPHM.38NPMPTW36.6YS6EN2CT7","price":"5.4902000000","Instance Type":"db.r5.24xlarge","LeaseContractLength":"3yr","plc:LeaseContractLength":"3 year","PurchaseOption":"Partial Upfront","Deployment Option":"Multi-AZ","Location":"AWS GovCloud (US-East)","Database Engine":"PostgreSQL","OnDemand:InstanceType":"db.r5.24xlarge","OnDemand:Location":"AWS GovCloud (US-East)","OnDemand:PricePerUnit":"28.9000000000","OnDemand:RateCode":"RZHFZ83TE35UPPHM.JRTCKXETXF.6YS6EN2CT7","riupfront:InstanceType":"db.r5.24xlarge","riupfront:Location":"AWS GovCloud (US-East)","riupfront:PricePerUnit":"144283.5072","riupfront:RateCode":"RZHFZ83TE35UPPHM.38NPMPTW36.2TG2D8R56U"},"PostgreSQL No license required db t3.2xlarge General purpose Multi-AZ 3 year Partial Upfront":{"rateCode":"T6UEYH3G6MSRAQGU.38NPMPTW36.6YS6EN2CT7","price":"0.3202000000","Instance Type":"db.t3.2xlarge","LeaseContractLength":"3yr","plc:LeaseContractLength":"3 year","PurchaseOption":"Partial Upfront","Deployment Option":"Multi-AZ","Location":"AWS GovCloud (US-East)","Database Engine":"PostgreSQL","OnDemand:InstanceType":"db.t3.2xlarge","OnDemand:Location":"AWS GovCloud (US-East)","OnDemand:PricePerUnit":"1.3900000000","OnDemand:RateCode":"T6UEYH3G6MSRAQGU.JRTCKXETXF.6YS6EN2CT7","riupfront:InstanceType":"db.t3.2xlarge","riupfront:Location":"AWS GovCloud (US-East)","riupfront:PricePerUnit":"8413.8048","riupfront:RateCode":"T6UEYH3G6MSRAQGU.38NPMPTW36.2TG2D8R56U"},"PostgreSQL No license required db m5.8xlarge General purpose Multi-AZ 3 year Partial Upfront":{"rateCode":"TVU9MZPPYDNPRF8P.38NPMPTW36.6YS6EN2CT7","price":"1.3975000000","Instance Type":"db.m5.8xlarge","LeaseContractLength":"3yr","plc:LeaseContractLength":"3 year","PurchaseOption":"Partial Upfront","Deployment Option":"Multi-AZ","Location":"AWS GovCloud (US-East)","Database Engine":"PostgreSQL","OnDemand:InstanceType":"db.m5.8xlarge","OnDemand:Location":"AWS GovCloud (US-East)","OnDemand:PricePerUnit":"6.8200000000","OnDemand:RateCode":"TVU9MZPPYDNPRF8P.JRTCKXETXF.6YS6EN2CT7","riupfront:InstanceType":"db.m5.8xlarge","riupfront:Location":"AWS GovCloud (US-East)","riupfront:PricePerUnit":"36725.6213","riupfront:RateCode":"TVU9MZPPYDNPRF8P.38NPMPTW36.2TG2D8R56U"},"PostgreSQL No license required db t4g.2xlarge General purpose Multi-AZ 3 year Partial Upfront":{"rateCode":"TZUNJT2UK7NP3SV7.38NPMPTW36.6YS6EN2CT7","price":"0.2478000000","Instance Type":"db.t4g.2xlarge","LeaseContractLength":"3yr","plc:LeaseContractLength":"3 year","PurchaseOption":"Partial Upfront","Deployment Option":"Multi-AZ","Location":"AWS GovCloud (US-East)","Database Engine":"PostgreSQL","OnDemand:InstanceType":"db.t4g.2xlarge","OnDemand:Location":"AWS GovCloud (US-East)","OnDemand:PricePerUnit":"1.1260000000","OnDemand:RateCode":"TZUNJT2UK7NP3SV7.JRTCKXETXF.6YS6EN2CT7","riupfront:InstanceType":"db.t4g.2xlarge","riupfront:Location":"AWS GovCloud (US-East)","riupfront:PricePerUnit":"6512","riupfront:RateCode":"TZUNJT2UK7NP3SV7.38NPMPTW36.2TG2D8R56U"},"PostgreSQL No license required db m5.4xlarge General purpose Multi-AZ 3 year Partial Upfront":{"rateCode":"VYFD5WH44K6VHXVJ.38NPMPTW36.6YS6EN2CT7","price":"0.6987000000","Instance Type":"db.m5.4xlarge","LeaseContractLength":"3yr","plc:LeaseContractLength":"3 year","PurchaseOption":"Partial Upfront","Deployment Option":"Multi-AZ","Location":"AWS GovCloud (US-East)","Database Engine":"PostgreSQL","OnDemand:InstanceType":"db.m5.4xlarge","OnDemand:Location":"AWS GovCloud (US-East)","OnDemand:PricePerUnit":"3.4100000000","OnDemand:RateCode":"VYFD5WH44K6VHXVJ.JRTCKXETXF.6YS6EN2CT7","riupfront:InstanceType":"db.m5.4xlarge","riupfront:Location":"AWS GovCloud (US-East)","riupfront:PricePerUnit":"18362.8107","riupfront:RateCode":"VYFD5WH44K6VHXVJ.38NPMPTW36.2TG2D8R56U"},"PostgreSQL No license required db r6g.2xlarge Memory optimized Multi-AZ 3 year Partial Upfront":{"rateCode":"W2EGYUGUG43P5MD2.38NPMPTW36.6YS6EN2CT7","price":"0.4115000000","Instance Type":"db.r6g.2xlarge","LeaseContractLength":"3yr","plc:LeaseContractLength":"3 year","PurchaseOption":"Partial Upfront","Deployment Option":"Multi-AZ","Location":"AWS GovCloud (US-East)","Database Engine":"PostgreSQL","OnDemand:InstanceType":"db.r6g.2xlarge","OnDemand:Location":"AWS GovCloud (US-East)","OnDemand:PricePerUnit":"2.1580000000","OnDemand:RateCode":"W2EGYUGUG43P5MD2.JRTCKXETXF.6YS6EN2CT7","riupfront:InstanceType":"db.r6g.2xlarge","riupfront:Location":"AWS GovCloud (US-East)","riupfront:PricePerUnit":"10814","riupfront:RateCode":"W2EGYUGUG43P5MD2.38NPMPTW36.2TG2D8R56U"},"PostgreSQL No license required db r6g.16xlarge Memory optimized Multi-AZ 3 year Partial Upfront":{"rateCode":"WQAR9DB4TAHXVBVF.38NPMPTW36.6YS6EN2CT7","price":"3.2920000000","Instance Type":"db.r6g.16xlarge","LeaseContractLength":"3yr","plc:LeaseContractLength":"3 year","PurchaseOption":"Partial Upfront","Deployment Option":"Multi-AZ","Location":"AWS GovCloud (US-East)","Database Engine":"PostgreSQL","OnDemand:InstanceType":"db.r6g.16xlarge","OnDemand:Location":"AWS GovCloud (US-East)","OnDemand:PricePerUnit":"17.2670000000","OnDemand:RateCode":"WQAR9DB4TAHXVBVF.JRTCKXETXF.6YS6EN2CT7","riupfront:InstanceType":"db.r6g.16xlarge","riupfront:Location":"AWS GovCloud (US-East)","riupfront:PricePerUnit":"86514","riupfront:RateCode":"WQAR9DB4TAHXVBVF.38NPMPTW36.2TG2D8R56U"},"PostgreSQL No license required db t3.small General purpose Multi-AZ 3 year Partial Upfront":{"rateCode":"XEBM99KMMWUUBRS6.38NPMPTW36.6YS6EN2CT7","price":"0.0200000000","Instance Type":"db.t3.small","LeaseContractLength":"3yr","plc:LeaseContractLength":"3 year","PurchaseOption":"Partial Upfront","Deployment Option":"Multi-AZ","Location":"AWS GovCloud (US-East)","Database Engine":"PostgreSQL","OnDemand:InstanceType":"db.t3.small","OnDemand:Location":"AWS GovCloud (US-East)","OnDemand:PricePerUnit":"0.0900000000","OnDemand:RateCode":"XEBM99KMMWUUBRS6.JRTCKXETXF.6YS6EN2CT7","riupfront:InstanceType":"db.t3.small","riupfront:Location":"AWS GovCloud (US-East)","riupfront:PricePerUnit":"525.8628","riupfront:RateCode":"XEBM99KMMWUUBRS6.38NPMPTW36.2TG2D8R56U"},"PostgreSQL No license required db r5.2xlarge Memory optimized Multi-AZ 3 year Partial Upfront":{"rateCode":"YJVQUE8455YW4ZMM.38NPMPTW36.6YS6EN2CT7","price":"0.4575000000","Instance Type":"db.r5.2xlarge","LeaseContractLength":"3yr","plc:LeaseContractLength":"3 year","PurchaseOption":"Partial Upfront","Deployment Option":"Multi-AZ","Location":"AWS GovCloud (US-East)","Database Engine":"PostgreSQL","OnDemand:InstanceType":"db.r5.2xlarge","OnDemand:Location":"AWS GovCloud (US-East)","OnDemand:PricePerUnit":"2.4100000000","OnDemand:RateCode":"YJVQUE8455YW4ZMM.JRTCKXETXF.6YS6EN2CT7","riupfront:InstanceType":"db.r5.2xlarge","riupfront:Location":"AWS GovCloud (US-East)","riupfront:PricePerUnit":"12023.6256","riupfront:RateCode":"YJVQUE8455YW4ZMM.38NPMPTW36.2TG2D8R56U"},"PostgreSQL No license required db m5.12xlarge General purpose Multi-AZ 3 year Partial Upfront":{"rateCode":"YU7PGKMTX2WU3K8V.38NPMPTW36.6YS6EN2CT7","price":"2.0962000000","Instance Type":"db.m5.12xlarge","LeaseContractLength":"3yr","plc:LeaseContractLength":"3 year","PurchaseOption":"Partial Upfront","Deployment Option":"Multi-AZ","Location":"AWS GovCloud (US-East)","Database Engine":"PostgreSQL","OnDemand:InstanceType":"db.m5.12xlarge","OnDemand:Location":"AWS GovCloud (US-East)","OnDemand:PricePerUnit":"10.2300000000","OnDemand:RateCode":"YU7PGKMTX2WU3K8V.JRTCKXETXF.6YS6EN2CT7","riupfront:InstanceType":"db.m5.12xlarge","riupfront:Location":"AWS GovCloud (US-East)","riupfront:PricePerUnit":"55088.432","riupfront:RateCode":"YU7PGKMTX2WU3K8V.38NPMPTW36.2TG2D8R56U"}}},"sets":{"Multi-AZ 3 year Partial Upfront AWS GovCloud US-East":["PostgreSQL No license required db t4g.medium General purpose Multi-AZ 3 year Partial Upfront","PostgreSQL No license required db m5.2xlarge General purpose Multi-AZ 3 year Partial Upfront","PostgreSQL No license required db m6g.16xlarge General purpose Multi-AZ 3 year Partial Upfront","PostgreSQL No license required db t3.xlarge General purpose Multi-AZ 3 year Partial Upfront","PostgreSQL No license required db m5.24xlarge General purpose Multi-AZ 3 year Partial Upfront","PostgreSQL No license required db r6g.8xlarge Memory optimized Multi-AZ 3 year Partial Upfront","PostgreSQL No license required db t4g.large General purpose Multi-AZ 3 year Partial Upfront","PostgreSQL No license required db r6g.large Memory optimized Multi-AZ 3 year Partial Upfront","PostgreSQL No license required db r5.12xlarge Memory optimized Multi-AZ 3 year Partial Upfront","PostgreSQL No license required db t4g.xlarge General purpose Multi-AZ 3 year Partial Upfront","PostgreSQL No license required db r6g.xlarge Memory optimized Multi-AZ 3 year Partial Upfront","PostgreSQL No license required db r5.8xlarge Memory optimized Multi-AZ 3 year Partial Upfront","PostgreSQL No license required db m5.16xlarge General purpose Multi-AZ 3 year Partial Upfront","PostgreSQL No license required db t3.large General purpose Multi-AZ 3 year Partial Upfront","PostgreSQL No license required db m6g.large General purpose Multi-AZ 3 year Partial Upfront","PostgreSQL No license required db r5.16xlarge Memory optimized Multi-AZ 3 year Partial Upfront","PostgreSQL No license required db r5.4xlarge Memory optimized Multi-AZ 3 year Partial Upfront","PostgreSQL No license required db r6g.12xlarge Memory optimized Multi-AZ 3 year Partial Upfront","PostgreSQL No license required db r5.large Memory optimized Multi-AZ 3 year Partial Upfront","PostgreSQL No license required db t3.medium General purpose Multi-AZ 3 year Partial Upfront","PostgreSQL No license required db m6g.2xlarge General purpose Multi-AZ 3 year Partial Upfront","PostgreSQL No license required db m5.xlarge General purpose Multi-AZ 3 year Partial Upfront","PostgreSQL No license required db m6g.8xlarge General purpose Multi-AZ 3 year Partial Upfront","PostgreSQL No license required db m6g.4xlarge General purpose Multi-AZ 3 year Partial Upfront","PostgreSQL No license required db m5.large General purpose Multi-AZ 3 year Partial Upfront","PostgreSQL No license required db r5.xlarge Memory optimized Multi-AZ 3 year Partial Upfront","PostgreSQL No license required db m6g.12xlarge General purpose Multi-AZ 3 year Partial Upfront","PostgreSQL No license required db m6g.xlarge General purpose Multi-AZ 3 year Partial Upfront","PostgreSQL No license required db t4g.small General purpose Multi-AZ 3 year Partial Upfront","PostgreSQL No license required db r6g.4xlarge Memory optimized Multi-AZ 3 year Partial Upfront","PostgreSQL No license required db r5.24xlarge Memory optimized Multi-AZ 3 year Partial Upfront","PostgreSQL No license required db t3.2xlarge General purpose Multi-AZ 3 year Partial Upfront","PostgreSQL No license required db m5.8xlarge General purpose Multi-AZ 3 year Partial Upfront","PostgreSQL No license required db t4g.2xlarge General purpose Multi-AZ 3 year Partial Upfront","PostgreSQL No license required db m5.4xlarge General purpose Multi-AZ 3 year Partial Upfront","PostgreSQL No license required db r6g.2xlarge Memory optimized Multi-AZ 3 year Partial Upfront","PostgreSQL No license required db r6g.16xlarge Memory optimized Multi-AZ 3 year Partial Upfront","PostgreSQL No license required db t3.small General purpose Multi-AZ 3 year Partial Upfront","PostgreSQL No license required db r5.2xlarge Memory optimized Multi-AZ 3 year Partial Upfront","PostgreSQL No license required db m5.12xlarge General purpose Multi-AZ 3 year Partial Upfront"]}}